{
  "type": "botanypots:crop",
  "seed": {
    "item": "passinggas:cabbage_seeds"
  },
  "categories": ["dirt", "farmland"],
  "growthTicks": 1200,
  "display": {
    "type": "botanypots:aging",
    "block": "passinggas:cabbage_crop"
  },
  "drops": [
    {
      "chance": 1,
      "output": {
        "item": "passinggas:cabbage"
      },
      "minRolls": 1,
      "maxRolls": 2
    },
    {
      "chance": 0.05,
      "output": {
        "item": "passinggas:cabbage_seeds"
      },
      "minRolls": 1,
      "maxRolls": 1
    }
  ],
  "bookshelf:load_conditions": [
    {
      "type": "bookshelf:item_exists",
      "values": ["passinggas:cabbage_seeds"]
    }
  ]
}
